setup.py
velcro/__init__.py
velcro/htmail.py
velcro/html.py
velcro/model.py
velcro/render.py
velcro/socks.py
velcro.egg-info/PKG-INFO
velcro.egg-info/SOURCES.txt
velcro.egg-info/dependency_links.txt
velcro.egg-info/requires.txt
velcro.egg-info/top_level.txt