Metadata-Version: 1.0
Name: velcro
Version: 0.3.0
Summary: Is awesome.
Home-page: UNKNOWN
Author: oakfang
Author-email: UNKNOWN
License: UNKNOWN
Platform: UNKNOWN
